{
 "channels*": [
  "mediapackage:ConfigureLogs",
  "mediapackage:DeleteChannel",
  "mediapackage:DescribeChannel",
  "mediapackage:RotateChannelCredentials",
  "mediapackage:RotateIngestEndpointCredentials",
  "mediapackage:UpdateChannel"
 ],
 "?": [
  "mediapackage:CreateChannel",
  "mediapackage:CreateHarvestJob",
  "mediapackage:CreateOriginEndpoint",
  "mediapackage:ListChannels",
  "mediapackage:ListHarvestJobs",
  "mediapackage:ListOriginEndpoints"
 ],
 "origin_endpoints*": [
  "mediapackage:DeleteOriginEndpoint",
  "mediapackage:DescribeOriginEndpoint",
  "mediapackage:UpdateOriginEndpoint"
 ],
 "harvest_jobs*": [
  "mediapackage:DescribeHarvestJob"
 ],
 "channels": [
  "mediapackage:ListTagsForResource",
  "mediapackage:TagResource",
  "mediapackage:UntagResource"
 ],
 "_url": "https://docs.aws.amazon.com/service-authorization/latest/reference/list_awselementalmediapackage.html"
}