{
 "server*": [
  "transfer:CreateAccess",
  "transfer:CreateAgreement",
  "transfer:CreateUser",
  "transfer:DeleteAccess",
  "transfer:DeleteServer",
  "transfer:DescribeAccess",
  "transfer:DescribeServer",
  "transfer:ImportHostKey",
  "transfer:ListAccesses",
  "transfer:ListAgreements",
  "transfer:ListHostKeys",
  "transfer:ListUsers",
  "transfer:StartServer",
  "transfer:StopServer",
  "transfer:UpdateServer"
 ],
 "?": [
  "transfer:CreateConnector",
  "transfer:CreateProfile",
  "transfer:CreateServer",
  "transfer:CreateWorkflow",
  "transfer:DescribeSecurityPolicy",
  "transfer:ImportCertificate",
  "transfer:ListCertificates",
  "transfer:ListConnectors",
  "transfer:ListProfiles",
  "transfer:ListSecurityPolicies",
  "transfer:ListServers",
  "transfer:ListWorkflows",
  "transfer:UpdateAccess"
 ],
 "agreement*": [
  "transfer:DeleteAgreement",
  "transfer:DescribeAgreement",
  "transfer:UpdateAgreement"
 ],
 "certificate*": [
  "transfer:DeleteCertificate",
  "transfer:DescribeCertificate",
  "transfer:UpdateCertificate"
 ],
 "connector*": [
  "transfer:DeleteConnector",
  "transfer:DescribeConnector",
  "transfer:StartFileTransfer",
  "transfer:UpdateConnector"
 ],
 "host-key*": [
  "transfer:DeleteHostKey",
  "transfer:DescribeHostKey",
  "transfer:UpdateHostKey"
 ],
 "profile*": [
  "transfer:DeleteProfile",
  "transfer:DescribeProfile",
  "transfer:UpdateProfile"
 ],
 "user*": [
  "transfer:DeleteSshPublicKey",
  "transfer:DeleteUser",
  "transfer:DescribeUser",
  "transfer:ImportSshPublicKey",
  "transfer:TestIdentityProvider",
  "transfer:UpdateUser"
 ],
 "workflow*": [
  "transfer:DeleteWorkflow",
  "transfer:DescribeExecution",
  "transfer:DescribeWorkflow",
  "transfer:ListExecutions",
  "transfer:SendWorkflowStepState"
 ],
 "agreement": [
  "transfer:ListTagsForResource",
  "transfer:TagResource",
  "transfer:UntagResource"
 ],
 "_url": "https://docs.aws.amazon.com/service-authorization/latest/reference/list_awstransferfamily.html"
}