{"channel*": ["kinesisvideo:ConnectAsMaster", "kinesisvideo:ConnectAsViewer", "kinesisvideo:CreateSignalingChannel", "kinesisvideo:DeleteSignalingChannel", "kinesisvideo:DescribeMediaStorageConfiguration", "kinesisvideo:DescribeSignalingChannel", "kinesisvideo:GetIceServerConfig", "kinesisvideo:GetSignalingChannelEndpoint", "kinesisvideo:JoinStorageSession", "kinesisvideo:SendAlexaOfferToMaster", "kinesisvideo:UpdateMediaStorageConfiguration", "kinesisvideo:UpdateSignalingChannel"], "stream*": ["kinesisvideo:CreateStream", "kinesisvideo:DeleteStream", "kinesisvideo:DescribeEdgeConfiguration", "kinesisvideo:DescribeImageGenerationConfiguration", "kinesisvideo:DescribeMappedResourceConfiguration", "kinesisvideo:DescribeNotificationConfiguration", "kinesisvideo:DescribeStream", "kinesisvideo:GetClip", "kinesisvideo:GetDASHStreamingSessionURL", "kinesisvideo:GetDataEndpoint", "kinesisvideo:GetHLSStreamingSessionURL", "kinesisvideo:GetImages", "kinesisvideo:GetMedia", "kinesisvideo:GetMediaForFragmentList", "kinesisvideo:ListFragments", "kinesisvideo:ListTagsForStream", "kinesisvideo:PutMedia", "kinesisvideo:StartEdgeConfigurationUpdate", "kinesisvideo:TagStream", "kinesisvideo:UntagStream", "kinesisvideo:UpdateDataRetention", "kinesisvideo:UpdateImageGenerationConfiguration", "kinesisvideo:UpdateNotificationConfiguration", "kinesisvideo:UpdateStream"], "?": ["kinesisvideo:ListSignalingChannels", "kinesisvideo:ListStreams"], "channel": ["kinesisvideo:ListTagsForResource", "kinesisvideo:TagResource", "kinesisvideo:UntagResource"], "_url": "https://docs.aws.amazon.com/service-authorization/latest/reference/list_amazonkinesisvideostreams.html"}